testrun/TestRun.py
testrun/__init__.py
testrun-1.0.0.dist-info/LICENSE
testrun-1.0.0.dist-info/METADATA
testrun-1.0.0.dist-info/WHEEL
testrun-1.0.0.dist-info/top_level.txt
testrun-1.0.0.dist-info/RECORD
