Metadata-Version: 2.1
Name: testrun
Version: 1.0.0
Summary: A package for tests with meaningful output and display (IDLE-Compatible)
Home-page: https://github.com/ES-Alexander/testrun
Author: ES-Alexander
License: UNKNOWN
Platform: UNKNOWN
Classifier: Programming Language :: Python :: 3
Classifier: License :: OSI Approved :: MIT License
Classifier: Operating System :: OS Independent
Requires-Python: >=3.6
